dataScipy/DataScience.py
dataScipy/__init__.py
dataScipy-0.0.4.0.5.2.dist-info/AUTHORS.md
dataScipy-0.0.4.0.5.2.dist-info/LICENCE
dataScipy-0.0.4.0.5.2.dist-info/METADATA
dataScipy-0.0.4.0.5.2.dist-info/WHEEL
dataScipy-0.0.4.0.5.2.dist-info/top_level.txt
dataScipy-0.0.4.0.5.2.dist-info/RECORD
